flutterby/__init__.py
flutterby/__main__.py
flutterby/command/__init__.py
flutterby/command/do_command.py
flutterby-0.0.0.dist-info/METADATA
flutterby-0.0.0.dist-info/WHEEL
flutterby-0.0.0.dist-info/RECORD
